odoo9_addon_l10n_be_antibiotic_tax-9.0.1.0.0.99.dev4-py2.7-nspkg.pth
odoo9_addon_l10n_be_antibiotic_tax-9.0.1.0.0.99.dev4.dist-info/METADATA
odoo9_addon_l10n_be_antibiotic_tax-9.0.1.0.0.99.dev4.dist-info/RECORD
odoo9_addon_l10n_be_antibiotic_tax-9.0.1.0.0.99.dev4.dist-info/WHEEL
odoo9_addon_l10n_be_antibiotic_tax-9.0.1.0.0.99.dev4.dist-info/namespace_packages.txt
odoo9_addon_l10n_be_antibiotic_tax-9.0.1.0.0.99.dev4.dist-info/top_level.txt
odoo_addons/l10n_be_antibiotic_tax/README.rst
odoo_addons/l10n_be_antibiotic_tax/__init__.py
odoo_addons/l10n_be_antibiotic_tax/__openerp__.py
odoo_addons/l10n_be_antibiotic_tax/data/account_account_template_data.xml
odoo_addons/l10n_be_antibiotic_tax/data/account_tax_code_template.xml
odoo_addons/l10n_be_antibiotic_tax/data/account_tax_template_antibiotic_in_data.xml
odoo_addons/l10n_be_antibiotic_tax/data/account_tax_template_antibiotic_out_data.xml
odoo_addons/l10n_be_antibiotic_tax/i18n/l10n_be_antibiotic_tax.pot
odoo_addons/l10n_be_antibiotic_tax/static/description/icon.png
